generic_pool/__init__.py
generic_pool/errors.py
generic_pool/factory.py
generic_pool/pool.py
generic_pool/queue_like.py
generic_pool-0.1.2.dist-info/LICENSE
generic_pool-0.1.2.dist-info/WHEEL
generic_pool-0.1.2.dist-info/METADATA
generic_pool-0.1.2.dist-info/RECORD
