Metadata-Version: 2.1
Name: generic-pool
Version: 0.1.2
Summary: A generic object pool implementation
Home-page: https://github.com/gfmio/generic-pool
License: MIT
Keywords: pool,generic
Author: Frédérique Mittelstaedt
Author-email: pypi@gfm.io
Requires-Python: >=3.8
Classifier: License :: OSI Approved :: MIT License
Classifier: Programming Language :: Python :: 3
Classifier: Programming Language :: Python :: 3.10
Classifier: Programming Language :: Python :: 3.8
Classifier: Programming Language :: Python :: 3.9
Project-URL: Documentation, https://github.com/gfmio/generic-pool
Project-URL: Repository, https://github.com/gfmio/generic-pool
